Metadata-Version: 2.4
Name: test-ryzenai-dynamic-dispatch
Version: 0.0.1
Summary: Dynamic dispatch on AMD IPU with RyzenAI
Author-email: AMD <support@amd.com>
Requires-Python: >=3.8
